rulita/__init__.py
rulita/exception/__init__.py
rulita/exception/api_error.py
rulita/util/__init__.py
rulita/util/file_system.py
rulita/util/logger.py
rulita-0.0.1.dist-info/licenses/LICENSE.txt
rulita-0.0.1.dist-info/METADATA
rulita-0.0.1.dist-info/WHEEL
rulita-0.0.1.dist-info/top_level.txt
rulita-0.0.1.dist-info/RECORD
