Metadata-Version: 2.4
Name: rulita
Version: 0.0.1
Summary: API Integrations for Social Media Platforms
Home-page: https://github.com/clivern/rulita/
Author: clivern
Author-email: hello@clivern.com
License: MIT
Project-URL: Documentation, https://github.com/clivern/rulita/
Project-URL: Source, https://github.com/clivern/rulita/
Project-URL: Changelog, https://github.com/clivern/rulita/blob/main/CHANGELOG.rst
Project-URL: Tracker, https://github.com/clivern/rulita/issues
Project-URL: Download, https://pypi.org/project/rulita/#files
Platform: any
Classifier: Development Status :: 5 - Production/Stable
Classifier: Programming Language :: Python
Classifier: License :: OSI Approved :: MIT License
License-File: LICENSE.txt
Requires-Dist: langchain<=0.3.22
Requires-Dist: langchain-openai<=0.3.11
Requires-Dist: openai<=1.63.2
Requires-Dist: requests<=2.32.3
Requires-Dist: importlib-metadata; python_version < "3.8"
Dynamic: license-file
